pynfogen/__init__.py
pynfogen/cli/__init__.py
pynfogen/cli/artwork.py
pynfogen/cli/config.py
pynfogen/cli/generate.py
pynfogen/cli/template.py
pynfogen/config.py
pynfogen/formatter.py
pynfogen/helpers.py
pynfogen/nfo.py
pynfogen/tracks/Audio.py
pynfogen/tracks/BaseTrack.py
pynfogen/tracks/Subtitle.py
pynfogen/tracks/Video.py
pynfogen/tracks/__init__.py
pynfogen-1.1.2.dist-info/entry_points.txt
pynfogen-1.1.2.dist-info/LICENSE
pynfogen-1.1.2.dist-info/WHEEL
pynfogen-1.1.2.dist-info/METADATA
pynfogen-1.1.2.dist-info/RECORD
