Metadata-Version: 2.1
Name: pynfogen
Version: 1.1.2
Summary: Scriptable MediaInfo-fed NFO Generator for Movies and TV
Home-page: https://github.com/rlaphoenix/pynfogen
License: MIT
Keywords: python,nfo,generator,scriptable
Author: PHOENiX
Author-email: rlaphoenix@pm.me
Requires-Python: >=3.7,<4.0
Classifier: Development Status :: 4 - Beta
Classifier: Environment :: Console
Classifier: Intended Audience :: End Users/Desktop
Classifier: License :: OSI Approved :: MIT License
Classifier: Natural Language :: English
Classifier: Operating System :: OS Independent
Classifier: Programming Language :: Python :: 3
Classifier: Programming Language :: Python :: 3.10
Classifier: Programming Language :: Python :: 3.7
Classifier: Programming Language :: Python :: 3.8
Classifier: Programming Language :: Python :: 3.9
Classifier: Topic :: Documentation
Classifier: Topic :: Multimedia
Classifier: Topic :: Multimedia :: Video
Requires-Dist: Unidecode (>=1.2.0,<2.0.0)
Requires-Dist: appdirs (>=1.4.4,<2.0.0)
Requires-Dist: click (>=8.0.0,<9.0.0)
Requires-Dist: click-default-group (>=1.2.2,<2.0.0)
Requires-Dist: dunamai (>=1.5.5,<2.0.0)
Requires-Dist: jsonpickle (>=2.1.0,<3.0.0)
Requires-Dist: langcodes[data] (>=3.3.0,<4.0.0)
Requires-Dist: pyd2v (>=1.3.0,<2.0.0)
Requires-Dist: pymediainfo (>=5.1.0,<6.0.0)
Requires-Dist: requests (>=2.25.1,<3.0.0)
Requires-Dist: tldextract (>=3.1.2,<4.0.0)
Project-URL: Documentation, https://github.com/rlaphoenix/pynfogen
Project-URL: Repository, https://github.com/rlaphoenix/pynfogen
